md2jira/__init__.py
md2jira/__main__.py
md2jira/jira_renderer.py
md2jira/md2jira.py
md2jira-1.0.1.dist-info/entry_points.txt
md2jira-1.0.1.dist-info/LICENSE
md2jira-1.0.1.dist-info/WHEEL
md2jira-1.0.1.dist-info/METADATA
md2jira-1.0.1.dist-info/RECORD
