Metadata-Version: 2.1
Name: md2jira
Version: 1.0.1
Summary: Markdown to jira
Home-page: https://pypi.org/project/md2jira
License: MIT
Author: Danil Akhtarov
Author-email: daxartio@gmail.com
Requires-Python: >=3.9,<4.0
Classifier: License :: OSI Approved :: MIT License
Classifier: Programming Language :: Python :: 3
Classifier: Programming Language :: Python :: 3.10
Classifier: Programming Language :: Python :: 3.9
Requires-Dist: mistletoe (>=0.8.2,<0.9.0)
Project-URL: Repository, https://github.com/daxartio/md2jira
